setup.py
html_clean/__init__.py
html_clean/clean.py
html_clean.egg-info/PKG-INFO
html_clean.egg-info/SOURCES.txt
html_clean.egg-info/dependency_links.txt
html_clean.egg-info/top_level.txt