Metadata-Version: 1.0
Name: html-clean
Version: 0.0.1
Summary: a library for remove useless html
Home-page: UNKNOWN
Author: GongBo
Author-email: 794928571@qq.com
License: MIT License
Keywords: html clean
Platform: any
